connector/__about__.py
connector/__init__.py
connector/auth_helper.py
connector/ca_certs.py
connector/cli.py
connector/client.py
connector/compile.py
connector/config.py
connector/error.py
connector/http_server.py
connector/httpx_rewrite.py
connector/integration.py
connector/main.py
connector/modules.py
connector/py.typed
connector/pydantic.py
connector/response_logging.py
connector/shared_types.py
connector/generated/__init__.py
connector/generated/models/__init__.py
connector/generated/models/account_status.py
connector/generated/models/account_type.py
connector/generated/models/activate_account.py
connector/generated/models/activate_account200_response.py
connector/generated/models/activate_account_request.py
connector/generated/models/activate_account_response.py
connector/generated/models/activated_account.py
connector/generated/models/activity_event_type.py
connector/generated/models/activity_record.py
connector/generated/models/activity_record_activity_type.py
connector/generated/models/activity_record_actor.py
connector/generated/models/activity_record_entitlement.py
connector/generated/models/activity_record_target.py
connector/generated/models/activity_type.py
connector/generated/models/amount.py
connector/generated/models/app_category.py
connector/generated/models/app_info.py
connector/generated/models/app_info200_response.py
connector/generated/models/app_info_request.py
connector/generated/models/app_info_request_payload.py
connector/generated/models/app_info_response.py
connector/generated/models/assign_entitlement.py
connector/generated/models/assign_entitlement200_response.py
connector/generated/models/assign_entitlement_request.py
connector/generated/models/assign_entitlement_response.py
connector/generated/models/assigned_entitlement.py
connector/generated/models/auth_credential.py
connector/generated/models/authorization_url.py
connector/generated/models/basic_authentication.py
connector/generated/models/basic_credential.py
connector_py-4.184.0.dist-info/licenses/LICENSE.txt
connector_py-4.184.0.dist-info/METADATA
connector_py-4.184.0.dist-info/WHEEL
connector_py-4.184.0.dist-info/entry_points.txt
connector_py-4.184.0.dist-info/top_level.txt
connector_py-4.184.0.dist-info/RECORD
