Metadata-Version: 2.4
Name: connector-py
Version: 4.184.0
Summary: An Abstract Tool to Perform Actions on Integrations.
Author-email: teamlumos <security@lumos.com>
License-Expression: Apache-2.0
Project-URL: Documentation, https://developers.lumos.com/reference/the-lumos-connector-api
Keywords: integrations
Classifier: Development Status :: 4 - Beta
Classifier: Programming Language :: Python
Classifier: Programming Language :: Python :: 3.10
Classifier: Programming Language :: Python :: 3.11
Classifier: Programming Language :: Python :: Implementation :: CPython
Classifier: Programming Language :: Python :: Implementation :: PyPy
Requires-Python: >=3.10
License-File: LICENSE.txt
Requires-Dist: connector-sdk-types==0.37.0
Requires-Dist: gql[httpx]
Requires-Dist: httpx>=0.27.0
Requires-Dist: msgpack>=1
Requires-Dist: pydantic<2.10,>=2
Requires-Dist: urllib3>=1.25.2
Requires-Dist: botocore>=1.34.0
Requires-Dist: PyJWT==2.10.1
Requires-Dist: datadog~=0.49.0
Requires-Dist: pip-system-certs==5.2; platform_system == "Windows"
Provides-Extra: fastapi
Requires-Dist: fastapi-slim; extra == "fastapi"
Requires-Dist: uvicorn; extra == "fastapi"
Provides-Extra: dev
Requires-Dist: pytest>=8; extra == "dev"
Requires-Dist: pytest-asyncio>=0.23; extra == "dev"
Requires-Dist: pytest-httpx>=0.33; extra == "dev"
Requires-Dist: Flask; extra == "dev"
Requires-Dist: pyinstaller>=6.8.0; extra == "dev"
Requires-Dist: pip-licenses>=5.0.0; extra == "dev"
Provides-Extra: all
Requires-Dist: connector-py[dev,fastapi]; extra == "all"
Dynamic: license-file
